{
  "outcomes": [
    {
      "context_hash": "a0be661c9495",
      "pattern_signature": "A1.0_B0.0_S0.0",
      "complexity_bucket": "HIGH",
      "size_bucket": "MEDIUM",
      "strategy_used": "arithmetic_pure",
      "success": true,
      "speedup_factor": 1.2977152688219353,
      "optimization_time_seconds": 4.63227765445111,
      "baseline_time_bucket": "MEDIUM",
      "improvement_category": "MEDIUM",
      "timestamp_week": "2025-W27",
      "anonymized_user_id": "48503cc823c00506",
      "privacy_noise_applied": true
    },
    {
      "context_hash": "a0be661c9495",
      "pattern_signature": "A1.0_B0.0_S0.0",
      "complexity_bucket": "HIGH",
      "size_bucket": "MEDIUM",
      "strategy_used": "arithmetic_pure",
      "success": true,
      "speedup_factor": 3.336394534088741,
      "optimization_time_seconds": 0.8389729210606942,
      "baseline_time_bucket": "MEDIUM",
      "improvement_category": "MEDIUM",
      "timestamp_week": "2025-W27",
      "anonymized_user_id": "48503cc823c00506",
      "privacy_noise_applied": true
    },
    {
      "context_hash": "a0be661c9495",
      "pattern_signature": "A1.0_B0.0_S0.0",
      "complexity_bucket": "HIGH",
      "size_bucket": "MEDIUM",
      "strategy_used": "arithmetic_pure",
      "success": true,
      "speedup_factor": 0.0,
      "optimization_time_seconds": 2.0201969069187253,
      "baseline_time_bucket": "MEDIUM",
      "improvement_category": "MEDIUM",
      "timestamp_week": "2025-W27",
      "anonymized_user_id": "48503cc823c00506",
      "privacy_noise_applied": true
    },
    {
      "context_hash": "a0be661c9495",
      "pattern_signature": "A1.0_B0.0_S0.0",
      "complexity_bucket": "HIGH",
      "size_bucket": "MEDIUM",
      "strategy_used": "arithmetic_pure",
      "success": true,
      "speedup_factor": 1.4444913565801183,
      "optimization_time_seconds": 2.4357899688393903,
      "baseline_time_bucket": "MEDIUM",
      "improvement_category": "MEDIUM",
      "timestamp_week": "2025-W27",
      "anonymized_user_id": "48503cc823c00506",
      "privacy_noise_applied": true
    },
    {
      "context_hash": "a0be661c9495",
      "pattern_signature": "A1.0_B0.0_S0.0",
      "complexity_bucket": "HIGH",
      "size_bucket": "MEDIUM",
      "strategy_used": "arithmetic_pure",
      "success": true,
      "speedup_factor": 1.553533833297159,
      "optimization_time_seconds": 1.0054097869890783,
      "baseline_time_bucket": "MEDIUM",
      "improvement_category": "MEDIUM",
      "timestamp_week": "2025-W27",
      "anonymized_user_id": "48503cc823c00506",
      "privacy_noise_applied": true
    },
    {
      "context_hash": "a0be661c9495",
      "pattern_signature": "A1.0_B0.0_S0.0",
      "complexity_bucket": "HIGH",
      "size_bucket": "MEDIUM",
      "strategy_used": "arithmetic_pure",
      "success": true,
      "speedup_factor": 2.142637555689717,
      "optimization_time_seconds": 2.9065158606232613,
      "baseline_time_bucket": "MEDIUM",
      "improvement_category": "MEDIUM",
      "timestamp_week": "2025-W27",
      "anonymized_user_id": "48503cc823c00506",
      "privacy_noise_applied": true
    },
    {
      "context_hash": "a0be661c9495",
      "pattern_signature": "A1.0_B0.0_S0.0",
      "complexity_bucket": "HIGH",
      "size_bucket": "MEDIUM",
      "strategy_used": "arithmetic_pure",
      "success": true,
      "speedup_factor": 1.9868223300435912,
      "optimization_time_seconds": 2.598267718960153,
      "baseline_time_bucket": "MEDIUM",
      "improvement_category": "MEDIUM",
      "timestamp_week": "2025-W27",
      "anonymized_user_id": "48503cc823c00506",
      "privacy_noise_applied": true
    },
    {
      "context_hash": "a0be661c9495",
      "pattern_signature": "A1.0_B0.0_S0.0",
      "complexity_bucket": "HIGH",
      "size_bucket": "MEDIUM",
      "strategy_used": "arithmetic_pure",
      "success": true,
      "speedup_factor": 2.145382671290054,
      "optimization_time_seconds": 2.4305366958693733,
      "baseline_time_bucket": "MEDIUM",
      "improvement_category": "MEDIUM",
      "timestamp_week": "2025-W27",
      "anonymized_user_id": "48503cc823c00506",
      "privacy_noise_applied": true
    },
    {
      "context_hash": "a0be661c9495",
      "pattern_signature": "A1.0_B0.0_S0.0",
      "complexity_bucket": "HIGH",
      "size_bucket": "MEDIUM",
      "strategy_used": "arithmetic_pure",
      "success": true,
      "speedup_factor": 0.5284755759865691,
      "optimization_time_seconds": 0.8206915687914804,
      "baseline_time_bucket": "MEDIUM",
      "improvement_category": "MEDIUM",
      "timestamp_week": "2025-W27",
      "anonymized_user_id": "48503cc823c00506",
      "privacy_noise_applied": true
    },
    {
      "context_hash": "a0be661c9495",
      "pattern_signature": "A1.0_B0.0_S0.0",
      "complexity_bucket": "HIGH",
      "size_bucket": "MEDIUM",
      "strategy_used": "arithmetic_pure",
      "success": true,
      "speedup_factor": 0.7444177479948105,
      "optimization_time_seconds": 3.4366159090498094,
      "baseline_time_bucket": "MEDIUM",
      "improvement_category": "MEDIUM",
      "timestamp_week": "2025-W27",
      "anonymized_user_id": "48503cc823c00506",
      "privacy_noise_applied": true
    }
  ],
  "privacy_level": "full",
  "upload_timestamp": "2025-07-07T23:42:46.903015",
  "client_version": "1.0.0"
}